nanonets_extractor/__init__.py
nanonets_extractor/cli.py
nanonets_extractor/exceptions.py
nanonets_extractor/extractor.py
nanonets_extractor/utils.py
nanonets_extractor/processors/__init__.py
nanonets_extractor/processors/base_processor.py
nanonets_extractor/processors/cloud_processor.py
nanonets_extractor-0.2.2.dist-info/licenses/LICENSE
nanonets_extractor-0.2.2.dist-info/METADATA
nanonets_extractor-0.2.2.dist-info/WHEEL
nanonets_extractor-0.2.2.dist-info/entry_points.txt
nanonets_extractor-0.2.2.dist-info/top_level.txt
nanonets_extractor-0.2.2.dist-info/RECORD
