Metadata-Version: 2.4
Name: nanonets-extractor
Version: 0.2.2
Summary: A Python library for extracting data from any document using AI
Home-page: https://github.com/nanonets/document-extractor
Author: Nanonets
Author-email: Nanonets <support@nanonets.com>
Maintainer-email: Nanonets <support@nanonets.com>
License: MIT
Project-URL: Homepage, https://github.com/nanonets/document-extractor
Project-URL: Documentation, https://docs.nanonets.com
Project-URL: Repository, https://github.com/nanonets/document-extractor
Project-URL: Bug Tracker, https://github.com/nanonets/document-extractor/issues
Keywords: document,extraction,pdf,ai,nanonets
Classifier: Development Status :: 4 - Beta
Classifier: Intended Audience :: Developers
Classifier: License :: OSI Approved :: MIT License
Classifier: Operating System :: OS Independent
Classifier: Programming Language :: Python :: 3
Classifier: Programming Language :: Python :: 3.8
Classifier: Programming Language :: Python :: 3.9
Classifier: Programming Language :: Python :: 3.10
Classifier: Programming Language :: Python :: 3.11
Classifier: Programming Language :: Python :: 3.12
Classifier: Topic :: Scientific/Engineering :: Artificial Intelligence
Classifier: Topic :: Software Development :: Libraries :: Python Modules
Classifier: Topic :: Text Processing :: General
Requires-Python: >=3.8
License-File: LICENSE
Requires-Dist: requests>=2.25.0
Provides-Extra: dev
Requires-Dist: pytest>=6.0.0; extra == "dev"
Requires-Dist: pytest-cov>=2.10.0; extra == "dev"
Requires-Dist: black>=21.0.0; extra == "dev"
Requires-Dist: flake8>=3.8.0; extra == "dev"
Requires-Dist: mypy>=0.910; extra == "dev"
Dynamic: author
Dynamic: home-page
Dynamic: license-file
Dynamic: requires-python
